topdog_cc/__init__.py
topdog_cc/aider.py
topdog_cc/bdd.py
topdog_cc/claude.py
topdog_cc/cli.py
topdog_cc/config.py
topdog_cc/domain.py
topdog_cc/feedback.py
topdog_cc/llm.py
topdog_cc/logger.py
topdog_cc/orchestrator.py
topdog_cc/radon.py
topdog_cc/reality.py
topdog_cc/tech_stack.py
topdog_cc-0.1.0.dist-info/licenses/LICENSE
topdog_cc-0.1.0.dist-info/METADATA
topdog_cc-0.1.0.dist-info/WHEEL
topdog_cc-0.1.0.dist-info/entry_points.txt
topdog_cc-0.1.0.dist-info/top_level.txt
topdog_cc-0.1.0.dist-info/RECORD
