Metadata-Version: 2.4
Name: topdog-cc
Version: 0.1.0
Summary: Conversation-aware multi-agent development framework with ∂-prefixed architecture
Author-email: TopDog Development <dev@topdog.cc>
Maintainer-email: TopDog Development <dev@topdog.cc>
License: MIT
Project-URL: Homepage, https://github.com/topdog-cc/topdog-cc
Project-URL: Repository, https://github.com/topdog-cc/topdog-cc
Project-URL: Documentation, https://github.com/topdog-cc/topdog-cc#readme
Project-URL: Bug Tracker, https://github.com/topdog-cc/topdog-cc/issues
Keywords: multi-agent,conversation-aware,development-framework,ai-tools,code-analysis,project-orchestration
Classifier: Development Status :: 4 - Beta
Classifier: Intended Audience :: Developers
Classifier: License :: OSI Approved :: MIT License
Classifier: Operating System :: OS Independent
Classifier: Programming Language :: Python :: 3
Classifier: Programming Language :: Python :: 3.8
Classifier: Programming Language :: Python :: 3.9
Classifier: Programming Language :: Python :: 3.10
Classifier: Programming Language :: Python :: 3.11
Classifier: Programming Language :: Python :: 3.12
Classifier: Topic :: Software Development :: Libraries :: Python Modules
Classifier: Topic :: Software Development :: Quality Assurance
Classifier: Topic :: Software Development :: Code Generators
Requires-Python: >=3.8
License-File: LICENSE
Provides-Extra: full
Requires-Dist: langmem; extra == "full"
Requires-Dist: langgraph; extra == "full"
Requires-Dist: openai; extra == "full"
Requires-Dist: anthropic; extra == "full"
Requires-Dist: radon; extra == "full"
Requires-Dist: behave; extra == "full"
Requires-Dist: aider-chat; extra == "full"
Provides-Extra: dev
Requires-Dist: pytest; extra == "dev"
Requires-Dist: black; extra == "dev"
Requires-Dist: flake8; extra == "dev"
Requires-Dist: mypy; extra == "dev"
Requires-Dist: build; extra == "dev"
Requires-Dist: twine; extra == "dev"
Dynamic: license-file
